eddie_chan_mcp/__init__.py
eddie_chan_mcp/main.py
eddie_chan_mcp-0.1.3.dist-info/METADATA
eddie_chan_mcp-0.1.3.dist-info/WHEEL
eddie_chan_mcp-0.1.3.dist-info/entry_points.txt
eddie_chan_mcp-0.1.3.dist-info/top_level.txt
eddie_chan_mcp-0.1.3.dist-info/RECORD
